dataframer/VERSION.txt
dataframer/__init__.py
dataframer/dataframer.py
dataframer-0.0.3.dist-info/LICENSE.txt
dataframer-0.0.3.dist-info/METADATA
dataframer-0.0.3.dist-info/RECORD
dataframer-0.0.3.dist-info/WHEEL
dataframer-0.0.3.dist-info/top_level.txt
