Metadata-Version: 2.1
Name: dataframer
Version: 0.0.3
Summary: Load any file into a pandas DataFrame, with a minimum of configuration, and a focus on bioinformatics
Home-page: https://github.com/refinery-platform/dataframer/
Author: Chuck McCallum
License: MIT License
Platform: UNKNOWN
Classifier: Intended Audience :: Developers
Classifier: License :: OSI Approved :: MIT License
Classifier: Operating System :: OS Independent
Classifier: Programming Language :: Python
Classifier: Programming Language :: Python :: 3.6
Requires-Dist: pandas
